download_youtube_subtitle/__init__.py
download_youtube_subtitle/__main__.py
download_youtube_subtitle/common.py
download_youtube_subtitle/main.py
download_youtube_subtitle/main_playlist.py
download_youtube_subtitle-3.0.2.dist-info/LICENSE
download_youtube_subtitle-3.0.2.dist-info/METADATA
download_youtube_subtitle-3.0.2.dist-info/WHEEL
download_youtube_subtitle-3.0.2.dist-info/entry_points.txt
download_youtube_subtitle-3.0.2.dist-info/top_level.txt
download_youtube_subtitle-3.0.2.dist-info/RECORD
