Metadata-Version: 2.1
Name: download-youtube-subtitle
Version: 3.0.2
Summary: download youtube subtitles(closed caption, cc) as txt or json
Home-page: https://github.com/xsthunder/download-youtube-subtitle
Author: xsthunder
Author-email: xsthunder@outlook.com
Classifier: Programming Language :: Python :: 3
Classifier: License :: OSI Approved :: MIT License
Classifier: Operating System :: OS Independent
Requires-Python: >=3.4
License-File: LICENSE
